globalmart_api5064/__init__.py
globalmart_api5064/api_dealer.py
globalmart_api5064-0.1.dist-info/License.txt
globalmart_api5064-0.1.dist-info/METADATA
globalmart_api5064-0.1.dist-info/WHEEL
globalmart_api5064-0.1.dist-info/top_level.txt
globalmart_api5064-0.1.dist-info/RECORD
